forest/benchmarking/__init__.py
forest/benchmarking/compilation.py
forest/benchmarking/direct_fidelity_estimation.py
forest/benchmarking/distance_measures.py
forest/benchmarking/entangled_states.py
forest/benchmarking/observable_estimation.py
forest/benchmarking/quantum_volume.py
forest/benchmarking/qubit_spectroscopy.py
forest/benchmarking/randomized_benchmarking.py
forest/benchmarking/readout.py
forest/benchmarking/robust_phase_estimation.py
forest/benchmarking/tomography.py
forest/benchmarking/utils.py
forest/benchmarking/analysis/__init__.py
forest/benchmarking/analysis/fitting.py
forest/benchmarking/classical_logic/__init__.py
forest/benchmarking/classical_logic/primitives.py
forest/benchmarking/classical_logic/ripple_carry_adder.py
forest/benchmarking/operator_tools/__init__.py
forest/benchmarking/operator_tools/apply_superoperator.py
forest/benchmarking/operator_tools/calculational.py
forest/benchmarking/operator_tools/channel_approximation.py
forest/benchmarking/operator_tools/compose_superoperators.py
forest/benchmarking/operator_tools/project_state_matrix.py
forest/benchmarking/operator_tools/project_superoperators.py
forest/benchmarking/operator_tools/random_operators.py
forest/benchmarking/operator_tools/superoperator_transformations.py
forest/benchmarking/operator_tools/validate_operator.py
forest/benchmarking/operator_tools/validate_superoperator.py
forest/benchmarking/plotting/__init__.py
forest/benchmarking/plotting/hinton.py
forest/benchmarking/plotting/state_process.py
forest/benchmarking/tests/__init__.py
forest/benchmarking/tests/conftest.py
forest/benchmarking/tests/test_apply_superoperator.py
forest/benchmarking/tests/test_calculational.py
forest/benchmarking/tests/test_channel_approximation.py
forest/benchmarking/tests/test_classical_logic_primites.py
forest/benchmarking/tests/test_compilation.py
forest/benchmarking/tests/test_compose_superoperators.py
forest/benchmarking/tests/test_direct_fidelity_estimation.py
forest_benchmarking-0.9.0.dist-info/LICENSE
forest_benchmarking-0.9.0.dist-info/METADATA
forest_benchmarking-0.9.0.dist-info/WHEEL
forest_benchmarking-0.9.0.dist-info/top_level.txt
forest_benchmarking-0.9.0.dist-info/RECORD
