Metadata-Version: 2.1
Name: forest-benchmarking
Version: 0.9.0
Summary: QCVV and Benchmarking
Home-page: http://rigetti.com
Author: Rigetti
Author-email: info@rigetti.com
License: Apache-2.0
License-File: LICENSE
Requires-Dist: pyquil <5.0.0,>=4.0.0
Requires-Dist: numpy
Requires-Dist: networkx
Requires-Dist: pandas
Requires-Dist: lmfit
Requires-Dist: scipy
Requires-Dist: sympy
Requires-Dist: python-rapidjson
Requires-Dist: cvxpy
Requires-Dist: tqdm
Requires-Dist: gitpython
Requires-Dist: matplotlib
